biggai-0.1.0.data/data/README.md
chain/__init__.py
chain/chain.py
chain/llm_main.py
chain/agent/__init__.py
chain/agent/agent.py
chain/agent/initialize.py
chain/agent/tools.py
chain/big_model/__init__.py
chain/big_model/agent_model.py
chain/big_model/base_model.py
chain/flow/__init__.py
chain/flow/initialize.py
chain/flow/chatflow/__init__.py
chain/flow/chatflow/llm.py
chain/flow/workflow/__init__.py
chain/flow/workflow/workflow.py
chain/flow/workflow/nodes/__init__.py
chain/flow/workflow/nodes/base_node.py
test/__init__.py
test/test_agent_.py
test/test_chain.py
test/test_flow_stream.py
biggai-0.1.0.dist-info/METADATA
biggai-0.1.0.dist-info/WHEEL
biggai-0.1.0.dist-info/top_level.txt
biggai-0.1.0.dist-info/RECORD
